cartnn/__init__.py
cartnn/_cartesian_harmonics.py
cartnn/_ictd.py
cartnn/_irreps.py
cartnn/_product_basis.py
cartnn/_utils.py
cartnn/_zemin.py
tace/__init__.py
tace/dataset/__init__.py
tace/dataset/dataloader.py
tace/dataset/datamodule.py
tace/dataset/element.py
tace/dataset/graph.py
tace/dataset/neighbour_list.py
tace/dataset/quantity.py
tace/dataset/read.py
tace/dataset/sampler.py
tace/dataset/split.py
tace/dataset/statistics.py
tace/dataset/utils.py
tace/foundations/__init__.py
tace/foundations/download_link.py
tace/interface/__init__.py
tace/interface/ase/__init__.py
tace/interface/ase/calculator.py
tace/interface/lammps/__init__.py
tace/interface/lammps/mliap.py
tace/interface/openmm/__init__.py
tace/interface/openmm/tacepotential.py
tace/interface/openmm/openmm-ml-main/setup.py
tace/interface/openmm/openmm-ml-main/build/lib/openmmml/__init__.py
tace/interface/openmm/openmm-ml-main/build/lib/openmmml/mlpotential.py
tace/interface/openmm/openmm-ml-main/build/lib/openmmml/models/__init__.py
tace/interface/openmm/openmm-ml-main/build/lib/openmmml/models/aimnet2potential.py
tace/interface/openmm/openmm-ml-main/build/lib/openmmml/models/anipotential.py
tace/interface/openmm/openmm-ml-main/build/lib/openmmml/models/deepmdpotential.py
tace/interface/openmm/openmm-ml-main/build/lib/openmmml/models/macepotential.py
tace/interface/openmm/openmm-ml-main/build/lib/openmmml/models/nequippotential.py
tace/interface/openmm/openmm-ml-main/build/lib/openmmml/models/torchmdnetpotential.py
tace/interface/openmm/openmm-ml-main/examples/nequip/run_nequip.py
tace/interface/openmm/openmm-ml-main/openmmml/__init__.py
tace/interface/openmm/openmm-ml-main/openmmml/mlpotential.py
tace/interface/openmm/openmm-ml-main/openmmml/models/__init__.py
tace/interface/openmm/openmm-ml-main/openmmml/models/aimnet2potential.py
tace/interface/openmm/openmm-ml-main/openmmml/models/anipotential.py
tace/interface/openmm/openmm-ml-main/openmmml/models/deepmdpotential.py
tace-0.0.9.dist-info/licenses/LICENSE.md
tace-0.0.9.dist-info/METADATA
tace-0.0.9.dist-info/WHEEL
tace-0.0.9.dist-info/entry_points.txt
tace-0.0.9.dist-info/top_level.txt
tace-0.0.9.dist-info/RECORD
