Metadata-Version: 2.4
Name: TACE
Version: 0.0.9
Summary: TACE - Irreducible Cartesian Tensor based equivariant atomistic model.
Author-email: Zemin Xu <xv_chana@163.com>
Project-URL: Homepage, https://github.com/xvzemin/tace
Requires-Python: >=3.10
License-File: LICENSE.md
Requires-Dist: torch<2.10
Requires-Dist: lightning
Requires-Dist: omegaconf
Requires-Dist: hydra-core>=1.3
Requires-Dist: matscipy
Requires-Dist: ase
Requires-Dist: numpy
Requires-Dist: e3nn
Requires-Dist: torch_geometric
Requires-Dist: scipy
Requires-Dist: configargparse
Requires-Dist: pandas
Requires-Dist: lmdb
Requires-Dist: torch-sim-atomistic!=0.5.0
Requires-Dist: wandb
Requires-Dist: huggingface_hub
Provides-Extra: cueq12
Requires-Dist: cuequivariance; extra == "cueq12"
Requires-Dist: cuequivariance-torch; extra == "cueq12"
Requires-Dist: cuequivariance-ops-torch-cu12; extra == "cueq12"
Provides-Extra: cueq13
Requires-Dist: cuequivariance; extra == "cueq13"
Requires-Dist: cuequivariance-torch; extra == "cueq13"
Requires-Dist: cuequivariance-ops-torch-cu13; extra == "cueq13"
Provides-Extra: oeq
Requires-Dist: openequivariance; extra == "oeq"
Provides-Extra: openmm
Requires-Dist: openmm; extra == "openmm"
Requires-Dist: openmm-ml; extra == "openmm"
Requires-Dist: openmmtorch; extra == "openmm"
Provides-Extra: lammps
Requires-Dist: lammps; extra == "lammps"
Requires-Dist: cython; extra == "lammps"
Requires-Dist: cupy-cuda12x; extra == "lammps"
Provides-Extra: d3
Requires-Dist: torch_dftd; extra == "d3"
Provides-Extra: nl
Requires-Dist: ase; extra == "nl"
Requires-Dist: matscipy; extra == "nl"
Requires-Dist: vesin; extra == "nl"
Provides-Extra: dev
Requires-Dist: sphinx; extra == "dev"
Requires-Dist: myst-parser; extra == "dev"
Requires-Dist: sphinx-copybutton; extra == "dev"
Requires-Dist: pydata-sphinx-theme; extra == "dev"
Requires-Dist: black; extra == "dev"
Requires-Dist: isort; extra == "dev"
Requires-Dist: pre-commit; extra == "dev"
Requires-Dist: MDAnalysis; extra == "dev"
Requires-Dist: tidynamics; extra == "dev"
Requires-Dist: mdtraj; extra == "dev"
Requires-Dist: scikit-learn; extra == "dev"
Requires-Dist: umap-learn; extra == "dev"
Requires-Dist: cotengra; extra == "dev"
Requires-Dist: optuna; extra == "dev"
Requires-Dist: cmaes; extra == "dev"
Requires-Dist: nevergrad; extra == "dev"
Requires-Dist: configargparse; extra == "dev"
Requires-Dist: ase_db_backends; extra == "dev"
Requires-Dist: tomli; extra == "dev"
Requires-Dist: matcalc; extra == "dev"
Requires-Dist: pandas; extra == "dev"
Requires-Dist: matminer; extra == "dev"
Requires-Dist: vtk; extra == "dev"
Requires-Dist: pymatgen; extra == "dev"
Requires-Dist: pymatviz==0.15.1; extra == "dev"
Requires-Dist: huggingface_hub; extra == "dev"
Dynamic: license-file
